{
  "comment": "Hunting Festival (Festa) soul-point milestone rewards, read by FestaRepository.ListPrizes (repo_festa.go), filtered by type. type: 'personal' or 'guild' track. tier: the festival team/rank tier (1-3) this reward applies to. souls_req: cumulative souls needed to unlock it. item_id/num_item: the reward item and quantity granted.",
  "rows": [
    {"type": "personal", "tier": 1, "souls_req": 1, "item_id": 9647, "num_item": 7},
    {"type": "personal", "tier": 2, "souls_req": 1, "item_id": 9647, "num_item": 7},
    {"type": "personal", "tier": 3, "souls_req": 1, "item_id": 9647, "num_item": 7},
    {"type": "personal", "tier": 1, "souls_req": 200, "item_id": 11284, "num_item": 4},
    {"type": "personal", "tier": 2, "souls_req": 200, "item_id": 11284, "num_item": 4},
    {"type": "personal", "tier": 3, "souls_req": 200, "item_id": 11284, "num_item": 4},
    {"type": "personal", "tier": 1, "souls_req": 400, "item_id": 11381, "num_item": 3},
    {"type": "personal", "tier": 2, "souls_req": 400, "item_id": 11381, "num_item": 3},
    {"type": "personal", "tier": 3, "souls_req": 400, "item_id": 11381, "num_item": 3},
    {"type": "personal", "tier": 1, "souls_req": 600, "item_id": 11284, "num_item": 8},
    {"type": "personal", "tier": 2, "souls_req": 600, "item_id": 11284, "num_item": 8},
    {"type": "personal", "tier": 3, "souls_req": 600, "item_id": 11284, "num_item": 8},
    {"type": "personal", "tier": 1, "souls_req": 800, "item_id": 11384, "num_item": 3},
    {"type": "personal", "tier": 2, "souls_req": 800, "item_id": 11384, "num_item": 3},
    {"type": "personal", "tier": 3, "souls_req": 800, "item_id": 11384, "num_item": 3},
    {"type": "personal", "tier": 1, "souls_req": 1000, "item_id": 11284, "num_item": 12},
    {"type": "personal", "tier": 2, "souls_req": 1000, "item_id": 11284, "num_item": 12},
    {"type": "personal", "tier": 3, "souls_req": 1000, "item_id": 11284, "num_item": 12},
    {"type": "personal", "tier": 1, "souls_req": 1200, "item_id": 11381, "num_item": 5},
    {"type": "personal", "tier": 2, "souls_req": 1200, "item_id": 11381, "num_item": 5},
    {"type": "personal", "tier": 3, "souls_req": 1200, "item_id": 11381, "num_item": 5},
    {"type": "personal", "tier": 1, "souls_req": 1400, "item_id": 11284, "num_item": 16},
    {"type": "personal", "tier": 2, "souls_req": 1400, "item_id": 11284, "num_item": 16},
    {"type": "personal", "tier": 3, "souls_req": 1400, "item_id": 11284, "num_item": 16},
    {"type": "personal", "tier": 1, "souls_req": 1700, "item_id": 11384, "num_item": 5},
    {"type": "personal", "tier": 2, "souls_req": 1700, "item_id": 11384, "num_item": 5},
    {"type": "personal", "tier": 3, "souls_req": 1700, "item_id": 11384, "num_item": 5},
    {"type": "personal", "tier": 1, "souls_req": 2000, "item_id": 11284, "num_item": 16},
    {"type": "personal", "tier": 2, "souls_req": 2000, "item_id": 11284, "num_item": 16},
    {"type": "personal", "tier": 3, "souls_req": 2000, "item_id": 11284, "num_item": 16},
    {"type": "personal", "tier": 1, "souls_req": 2500, "item_id": 11382, "num_item": 4},
    {"type": "personal", "tier": 2, "souls_req": 2500, "item_id": 11382, "num_item": 4},
    {"type": "personal", "tier": 3, "souls_req": 2500, "item_id": 11382, "num_item": 4},
    {"type": "personal", "tier": 1, "souls_req": 3000, "item_id": 11284, "num_item": 24},
    {"type": "personal", "tier": 2, "souls_req": 3000, "item_id": 11284, "num_item": 24},
    {"type": "personal", "tier": 3, "souls_req": 3000, "item_id": 11284, "num_item": 24},
    {"type": "personal", "tier": 1, "souls_req": 4000, "item_id": 11385, "num_item": 4},
    {"type": "personal", "tier": 2, "souls_req": 4000, "item_id": 11385, "num_item": 4},
    {"type": "personal", "tier": 3, "souls_req": 4000, "item_id": 11385, "num_item": 4},
    {"type": "personal", "tier": 1, "souls_req": 5000, "item_id": 11381, "num_item": 11},
    {"type": "personal", "tier": 2, "souls_req": 5000, "item_id": 11381, "num_item": 11},
    {"type": "personal", "tier": 3, "souls_req": 5000, "item_id": 11381, "num_item": 11},
    {"type": "personal", "tier": 1, "souls_req": 6000, "item_id": 5177, "num_item": 5},
    {"type": "personal", "tier": 2, "souls_req": 6000, "item_id": 5177, "num_item": 5},
    {"type": "personal", "tier": 3, "souls_req": 6000, "item_id": 5177, "num_item": 5},
    {"type": "personal", "tier": 1, "souls_req": 7000, "item_id": 11384, "num_item": 11},
    {"type": "personal", "tier": 2, "souls_req": 7000, "item_id": 11384, "num_item": 11},
    {"type": "personal", "tier": 3, "souls_req": 7000, "item_id": 11384, "num_item": 11},
    {"type": "personal", "tier": 1, "souls_req": 10000, "item_id": 11382, "num_item": 8},
    {"type": "personal", "tier": 2, "souls_req": 10000, "item_id": 11382, "num_item": 8},
    {"type": "personal", "tier": 3, "souls_req": 10000, "item_id": 11382, "num_item": 8},
    {"type": "personal", "tier": 1, "souls_req": 15000, "item_id": 11385, "num_item": 4},
    {"type": "personal", "tier": 2, "souls_req": 15000, "item_id": 11385, "num_item": 4},
    {"type": "personal", "tier": 3, "souls_req": 15000, "item_id": 11385, "num_item": 4},
    {"type": "personal", "tier": 1, "souls_req": 20000, "item_id": 11381, "num_item": 13},
    {"type": "personal", "tier": 2, "souls_req": 20000, "item_id": 11381, "num_item": 13},
    {"type": "personal", "tier": 3, "souls_req": 20000, "item_id": 11381, "num_item": 13},
    {"type": "personal", "tier": 1, "souls_req": 25000, "item_id": 11385, "num_item": 4},
    {"type": "personal", "tier": 2, "souls_req": 25000, "item_id": 11385, "num_item": 4},
    {"type": "personal", "tier": 3, "souls_req": 25000, "item_id": 11385, "num_item": 4},
    {"type": "personal", "tier": 1, "souls_req": 30000, "item_id": 11383, "num_item": 1},
    {"type": "personal", "tier": 2, "souls_req": 30000, "item_id": 11383, "num_item": 1},
    {"type": "personal", "tier": 3, "souls_req": 30000, "item_id": 11383, "num_item": 1},
    {"type": "guild", "tier": 1, "souls_req": 100, "item_id": 7468, "num_item": 5},
    {"type": "guild", "tier": 2, "souls_req": 100, "item_id": 7468, "num_item": 5},
    {"type": "guild", "tier": 3, "souls_req": 100, "item_id": 7465, "num_item": 5},
    {"type": "guild", "tier": 1, "souls_req": 300, "item_id": 7469, "num_item": 5},
    {"type": "guild", "tier": 2, "souls_req": 300, "item_id": 7469, "num_item": 5},
    {"type": "guild", "tier": 3, "souls_req": 300, "item_id": 7466, "num_item": 5},
    {"type": "guild", "tier": 1, "souls_req": 700, "item_id": 7470, "num_item": 5},
    {"type": "guild", "tier": 2, "souls_req": 700, "item_id": 7470, "num_item": 5},
    {"type": "guild", "tier": 3, "souls_req": 700, "item_id": 7467, "num_item": 5},
    {"type": "guild", "tier": 1, "souls_req": 1500, "item_id": 13405, "num_item": 14},
    {"type": "guild", "tier": 1, "souls_req": 1500, "item_id": 1520, "num_item": 3},
    {"type": "guild", "tier": 2, "souls_req": 1500, "item_id": 13405, "num_item": 14},
    {"type": "guild", "tier": 2, "souls_req": 1500, "item_id": 1520, "num_item": 3},
    {"type": "guild", "tier": 3, "souls_req": 1500, "item_id": 7011, "num_item": 3},
    {"type": "guild", "tier": 3, "souls_req": 1500, "item_id": 13405, "num_item": 14},
    {"type": "guild", "tier": 1, "souls_req": 3000, "item_id": 10201, "num_item": 10},
    {"type": "guild", "tier": 2, "souls_req": 3000, "item_id": 10201, "num_item": 10},
    {"type": "guild", "tier": 3, "souls_req": 3000, "item_id": 10201, "num_item": 10},
    {"type": "guild", "tier": 1, "souls_req": 6000, "item_id": 13895, "num_item": 14},
    {"type": "guild", "tier": 1, "souls_req": 6000, "item_id": 1520, "num_item": 6},
    {"type": "guild", "tier": 2, "souls_req": 6000, "item_id": 13895, "num_item": 14},
    {"type": "guild", "tier": 2, "souls_req": 6000, "item_id": 1520, "num_item": 6},
    {"type": "guild", "tier": 3, "souls_req": 6000, "item_id": 13895, "num_item": 14},
    {"type": "guild", "tier": 3, "souls_req": 6000, "item_id": 7011, "num_item": 4},
    {"type": "guild", "tier": 1, "souls_req": 12000, "item_id": 13406, "num_item": 14},
    {"type": "guild", "tier": 1, "souls_req": 12000, "item_id": 1520, "num_item": 9},
    {"type": "guild", "tier": 2, "souls_req": 12000, "item_id": 13406, "num_item": 14},
    {"type": "guild", "tier": 2, "souls_req": 12000, "item_id": 1520, "num_item": 9},
    {"type": "guild", "tier": 3, "souls_req": 12000, "item_id": 13406, "num_item": 14},
    {"type": "guild", "tier": 3, "souls_req": 12000, "item_id": 7011, "num_item": 5},
    {"type": "guild", "tier": 1, "souls_req": 25000, "item_id": 10207, "num_item": 10},
    {"type": "guild", "tier": 2, "souls_req": 25000, "item_id": 10207, "num_item": 10},
    {"type": "guild", "tier": 3, "souls_req": 25000, "item_id": 10207, "num_item": 10},
    {"type": "guild", "tier": 1, "souls_req": 50000, "item_id": 1520, "num_item": 12},
    {"type": "guild", "tier": 1, "souls_req": 50000, "item_id": 13896, "num_item": 14},
    {"type": "guild", "tier": 2, "souls_req": 50000, "item_id": 1520, "num_item": 12},
    {"type": "guild", "tier": 2, "souls_req": 50000, "item_id": 13896, "num_item": 14},
    {"type": "guild", "tier": 3, "souls_req": 50000, "item_id": 7011, "num_item": 6},
    {"type": "guild", "tier": 3, "souls_req": 50000, "item_id": 13896, "num_item": 14},
    {"type": "guild", "tier": 1, "souls_req": 100000, "item_id": 10201, "num_item": 10},
    {"type": "guild", "tier": 2, "souls_req": 100000, "item_id": 10201, "num_item": 10},
    {"type": "guild", "tier": 3, "souls_req": 100000, "item_id": 10201, "num_item": 10},
    {"type": "guild", "tier": 1, "souls_req": 200000, "item_id": 13406, "num_item": 16},
    {"type": "guild", "tier": 2, "souls_req": 200000, "item_id": 13406, "num_item": 16},
    {"type": "guild", "tier": 3, "souls_req": 200000, "item_id": 13406, "num_item": 16},
    {"type": "guild", "tier": 1, "souls_req": 300000, "item_id": 13896, "num_item": 16},
    {"type": "guild", "tier": 2, "souls_req": 300000, "item_id": 13896, "num_item": 16},
    {"type": "guild", "tier": 3, "souls_req": 300000, "item_id": 13896, "num_item": 16},
    {"type": "guild", "tier": 1, "souls_req": 400000, "item_id": 10207, "num_item": 10},
    {"type": "guild", "tier": 2, "souls_req": 400000, "item_id": 10207, "num_item": 10},
    {"type": "guild", "tier": 3, "souls_req": 400000, "item_id": 10207, "num_item": 10},
    {"type": "guild", "tier": 1, "souls_req": 500000, "item_id": 13407, "num_item": 6},
    {"type": "guild", "tier": 1, "souls_req": 500000, "item_id": 13897, "num_item": 6},
    {"type": "guild", "tier": 2, "souls_req": 500000, "item_id": 13407, "num_item": 6},
    {"type": "guild", "tier": 2, "souls_req": 500000, "item_id": 13897, "num_item": 6},
    {"type": "guild", "tier": 3, "souls_req": 500000, "item_id": 13407, "num_item": 6},
    {"type": "guild", "tier": 3, "souls_req": 500000, "item_id": 13897, "num_item": 6}
  ]
}
